nexTextract/__init__.py
nexTextract/_nbdev.py
nexTextract/core.py
nexTextract-0.0.1.dist-info/LICENSE
nexTextract-0.0.1.dist-info/METADATA
nexTextract-0.0.1.dist-info/WHEEL
nexTextract-0.0.1.dist-info/entry_points.txt
nexTextract-0.0.1.dist-info/top_level.txt
nexTextract-0.0.1.dist-info/RECORD
