Metadata-Version: 2.1
Name: nexTextract
Version: 0.0.1
Summary: This library is for extracting knowedge graphs from natural text using transformer models and reinforcement learning.
Home-page: https://github.com/MartinJohannessen/nexTextract/tree/master/
Author: Martin Skivenesvåg Johannessen
Author-email: xin004@uib.no
License: Apache Software License 2.0
Keywords: Transformer models,T5,BERT,webNLG,RDF,Knowledge graph,Reinforcement learning,RL,PPO.
Platform: UNKNOWN
Classifier: Development Status :: 3 - Alpha
Classifier: Intended Audience :: Developers
Classifier: Natural Language :: English
Classifier: Programming Language :: Python :: 3.6
Classifier: Programming Language :: Python :: 3.7
Classifier: Programming Language :: Python :: 3.8
Classifier: License :: OSI Approved :: Apache Software License
Requires-Python: >=3.6
License-File: LICENSE
Requires-Dist: pip
Requires-Dist: packaging
Provides-Extra: dev
